{
  "ticket": "MTO-31",
  "currentPhase": "done",
  "phases": {
    "requirements": { "status": "done", "file": "BRD.md", "version": 1, "completedAt": "2026-05-08T12:00:00Z" },
    "specification": { "status": "done", "file": "FSD.md", "version": 1, "completedAt": "2026-05-08T13:00:00Z" },
    "design": { "status": "done", "file": "TDD.md", "version": 1, "completedAt": "2026-05-08T14:00:00Z" },
    "feedback_loop": { "status": "done", "iterations": 0, "maxIterations": 5 },
    "test_planning": { "status": "done", "file": "STP.md", "version": 1, "completedAt": "2026-05-08T15:00:00Z" },
    "implementation": { "status": "done", "completedAt": "2026-05-08T16:00:00Z" },
    "testing": { "status": "done", "completedAt": "2026-05-08T16:45:00Z", "results": "12/12 unit tests PASSED, integration tests skipped (Docker unavailable)" }
  },
  "lastUpdated": "2026-05-08T16:45:00Z",
  "notes": "KB server unavailable for ingestion. Docker not available for Testcontainers integration tests."
}
